<?xml version="1.0" encoding="UTF-8"?><element type_str="object" name_str="root"><element type_str="string" name_str="title"><![CDATA[layout]]></element><element type_str="string" name_str="deeplink"><![CDATA[start/menu/manage/manage.edit/advanced/layout]]></element><element type_str="string" name_str="pubDate"><![CDATA[Sat Jul 11 14:03:24 GMT+0200 2009]]></element><element type_str="string" name_str="urlBase"><![CDATA[http://localhost:8888/Trunk silex/silex_server/manager/]]></element><element type_str="object" name_str="content"><element type_str="object" name_str="0"><element type_str="string" name_str="context"><![CDATA[*]]></element><element type_str="string" name_str="text"><![CDATA[((<<silex.config.siteConfTxt.loaderSkinUrl>>))]]></element><element type_str="string" name_str="htmlEquivalent"><![CDATA[<p><TEXTFORMAT LEADING="2"><P ALIGN="LEFT"><FONT FACE="Arial" SIZE="17" COLOR="#FFFFFF" LETTERSPACING="0" KERNING="0">((&lt;&lt;silex.config.siteConfTxt.loaderSkinUrl&gt;&gt;))</FONT></P></TEXTFORMAT></p>]]></element></element><element type_str="object" name_str="1"><element type_str="string" name_str="context"><![CDATA[*]]></element><element type_str="string" name_str="htmlEquivalent"><![CDATA[<object classid="clsid:d27cdb6e-ae6d-11cf-96b8-444553540000" codebase="http://fpdownload.macromedia.com/pub/shockwave/cabs/flash/swflash.cab#version=8,0,0,0" width="190" height="0.5" ><param name="movie" value="../../../../../../../media/manager/design/filet_horizontal.swf" /><param name="quality" value="best" /><param name="bgcolor" value="#303030" /><embed src = "../../../../../../../media/manager/design/filet_horizontal.swf" quality = "best" bgcolor = "#303030" width = "190" height = "0.5" type = "application/x-shockwave-flash" pluginspage = "http://www.macromedia.com/go/getflashplayer" /></object>]]></element></element><element type_str="object" name_str="2"><element type_str="object" name_str="links"><element type_str="object" name_str="0"><element type_str="string" name_str="title"><![CDATA[gabaritcalque]]></element><element type_str="string" name_str="link"><![CDATA[gabaritcalque]]></element></element></element><element type_str="string" name_str="context"><![CDATA[*]]></element><element type_str="string" name_str="text"><![CDATA[...]]></element><element type_str="string" name_str="htmlEquivalent"><![CDATA[<p><TEXTFORMAT LEADING="2"><P ALIGN="LEFT"><FONT FACE="Arial" SIZE="17" COLOR="#000000" LETTERSPACING="0" KERNING="0">...</FONT></P></TEXTFORMAT></p>]]></element></element><element type_str="object" name_str="3"><element type_str="object" name_str="links"><element type_str="object" name_str="0"><element type_str="string" name_str="title"><![CDATA[loader]]></element><element type_str="string" name_str="link"><![CDATA[loader]]></element></element></element><element type_str="string" name_str="context"><![CDATA[*]]></element><element type_str="string" name_str="text"><![CDATA[...]]></element><element type_str="string" name_str="htmlEquivalent"><![CDATA[<p><TEXTFORMAT LEADING="2"><P ALIGN="LEFT"><FONT FACE="Arial" SIZE="17" COLOR="#000000" LETTERSPACING="0" KERNING="0">...</FONT></P></TEXTFORMAT></p>]]></element></element><element type_str="object" name_str="4"><element type_str="object" name_str="links"><element type_str="object" name_str="0"><element type_str="string" name_str="title"><![CDATA[gabaritpage]]></element><element type_str="string" name_str="link"><![CDATA[gabaritpage]]></element></element></element><element type_str="string" name_str="context"><![CDATA[*]]></element><element type_str="string" name_str="text"><![CDATA[...]]></element><element type_str="string" name_str="htmlEquivalent"><![CDATA[<p><TEXTFORMAT LEADING="2"><P ALIGN="LEFT"><FONT FACE="Arial" SIZE="17" COLOR="#000000" LETTERSPACING="0" KERNING="0">...</FONT></P></TEXTFORMAT></p>]]></element></element><element type_str="object" name_str="5"><element type_str="string" name_str="context"><![CDATA[*]]></element><element type_str="string" name_str="htmlEquivalent"><![CDATA[<object classid="clsid:d27cdb6e-ae6d-11cf-96b8-444553540000" codebase="http://fpdownload.macromedia.com/pub/shockwave/cabs/flash/swflash.cab#version=8,0,0,0" width="190" height="0.5" ><param name="movie" value="../../../../../../../media/manager/design/filet_horizontal.swf" /><param name="quality" value="best" /><param name="bgcolor" value="#303030" /><embed src = "../../../../../../../media/manager/design/filet_horizontal.swf" quality = "best" bgcolor = "#303030" width = "190" height = "0.5" type = "application/x-shockwave-flash" pluginspage = "http://www.macromedia.com/go/getflashplayer" /></object>]]></element></element><element type_str="object" name_str="6"><element type_str="string" name_str="context"><![CDATA[*]]></element><element type_str="string" name_str="htmlEquivalent"><![CDATA[<object classid="clsid:d27cdb6e-ae6d-11cf-96b8-444553540000" codebase="http://fpdownload.macromedia.com/pub/shockwave/cabs/flash/swflash.cab#version=8,0,0,0" width="228" height="0.5" ><param name="movie" value="../../../../../../../media/manager/design/filet_horizontal.swf" /><param name="quality" value="best" /><param name="bgcolor" value="#303030" /><embed src = "../../../../../../../media/manager/design/filet_horizontal.swf" quality = "best" bgcolor = "#303030" width = "228" height = "0.5" type = "application/x-shockwave-flash" pluginspage = "http://www.macromedia.com/go/getflashplayer" /></object>]]></element></element><element type_str="object" name_str="7"><element type_str="string" name_str="context"><![CDATA[*]]></element><element type_str="string" name_str="htmlEquivalent"><![CDATA[<object classid="clsid:d27cdb6e-ae6d-11cf-96b8-444553540000" codebase="http://fpdownload.macromedia.com/pub/shockwave/cabs/flash/swflash.cab#version=8,0,0,0" width="190" height="0.5" ><param name="movie" value="../../../../../../../media/manager/design/filet_horizontal.swf" /><param name="quality" value="best" /><param name="bgcolor" value="#303030" /><embed src = "../../../../../../../media/manager/design/filet_horizontal.swf" quality = "best" bgcolor = "#303030" width = "190" height = "0.5" type = "application/x-shockwave-flash" pluginspage = "http://www.macromedia.com/go/getflashplayer" /></object>]]></element></element><element type_str="object" name_str="8"><element type_str="string" name_str="context"><![CDATA[*]]></element><element type_str="string" name_str="text"><![CDATA[((<<silex.paramsFile.btn:manage:save>>))]]></element><element type_str="string" name_str="htmlEquivalent"><![CDATA[<p><TEXTFORMAT LEADING="2"><P ALIGN="LEFT"><FONT FACE="Arial" SIZE="17" COLOR="#FFFFFF" LETTERSPACING="0" KERNING="0"><B>((&lt;&lt;silex.paramsFile.btn:manage:save&gt;&gt;))</B></FONT></P></TEXTFORMAT></p>]]></element></element><element type_str="object" name_str="9"><element type_str="string" name_str="context"><![CDATA[*]]></element><element type_str="string" name_str="text"><![CDATA[((<<silex.config.siteConfTxt.initialLayoutFile>>))]]></element><element type_str="string" name_str="htmlEquivalent"><![CDATA[<p><TEXTFORMAT LEADING="2"><P ALIGN="LEFT"><FONT FACE="arial" SIZE="17" COLOR="#FFFFFF" LETTERSPACING="0" KERNING="0">((&lt;&lt;silex.config.siteConfTxt.initialLayoutFile&gt;&gt;))</FONT></P></TEXTFORMAT></p>]]></element></element><element type_str="object" name_str="10"><element type_str="string" name_str="context"><![CDATA[*]]></element><element type_str="string" name_str="text"><![CDATA[((<<silex.config.siteConfTxt.layerSkinUrl>>))]]></element><element type_str="string" name_str="htmlEquivalent"><![CDATA[<p><TEXTFORMAT LEADING="2"><P ALIGN="LEFT"><FONT FACE="arial" SIZE="17" COLOR="#FFFFFF" LETTERSPACING="0" KERNING="0">((&lt;&lt;silex.config.siteConfTxt.layerSkinUrl&gt;&gt;))</FONT></P></TEXTFORMAT></p>]]></element></element><element type_str="object" name_str="11"><element type_str="string" name_str="context"><![CDATA[*]]></element><element type_str="string" name_str="text"><![CDATA[((<<silex.config.siteConfTxt.toolsFolderRelativePath>>))]]></element><element type_str="string" name_str="htmlEquivalent"><![CDATA[<p><TEXTFORMAT LEADING="2"><P ALIGN="LEFT"><FONT FACE="arial" SIZE="17" COLOR="#FFFFFF" LETTERSPACING="0" KERNING="0">((&lt;&lt;silex.config.siteConfTxt.toolsFolderRelativePath&gt;&gt;))</FONT></P></TEXTFORMAT></p>]]></element></element><element type_str="object" name_str="12"><element type_str="string" name_str="context"><![CDATA[*]]></element><element type_str="string" name_str="text"><![CDATA[((<<silex.paramsFile.manage:text:34>>))((<<silex.paramsFile.manage:text:35>>))((<<silex.paramsFile.manage:text:33>>))((<<silex.paramsFile.manage:text:36>>))]]></element><element type_str="string" name_str="htmlEquivalent"><![CDATA[<p><TEXTFORMAT LEADING="21"><P ALIGN="LEFT"><FONT FACE="arial" SIZE="17" COLOR="#AAAAAA" LETTERSPACING="0" KERNING="0">((&lt;&lt;silex.paramsFile.manage:text:34&gt;&gt;))</FONT></P></TEXTFORMAT><TEXTFORMAT LEADING="21"><P ALIGN="LEFT"><FONT FACE="arial" SIZE="17" COLOR="#AAAAAA" LETTERSPACING="0" KERNING="0">((&lt;&lt;silex.paramsFile.manage:text:35&gt;&gt;))</FONT></P></TEXTFORMAT><TEXTFORMAT LEADING="21"><P ALIGN="LEFT"><FONT FACE="arial" SIZE="17" COLOR="#AAAAAA" LETTERSPACING="0" KERNING="0">((&lt;&lt;silex.paramsFile.manage:text:33&gt;&gt;))</FONT></P></TEXTFORMAT><TEXTFORMAT LEADING="2"><P ALIGN="LEFT"><FONT FACE="arial" SIZE="17" COLOR="#AAAAAA" LETTERSPACING="0" KERNING="0">((&lt;&lt;silex.paramsFile.manage:text:36&gt;&gt;))</FONT></P></TEXTFORMAT></p>]]></element></element><element type_str="object" name_str="13"><element type_str="string" name_str="context"><![CDATA[*]]></element><element type_str="string" name_str="htmlEquivalent"><![CDATA[<object classid="clsid:d27cdb6e-ae6d-11cf-96b8-444553540000" codebase="http://fpdownload.macromedia.com/pub/shockwave/cabs/flash/swflash.cab#version=8,0,0,0" width="560" height="111.35" ><param name="movie" value="../../../../../../../media/manager/design/bandes_grises_30.swf" /><param name="quality" value="best" /><param name="bgcolor" value="#303030" /><embed src = "../../../../../../../media/manager/design/bandes_grises_30.swf" quality = "best" bgcolor = "#303030" width = "560" height = "111.35" type = "application/x-shockwave-flash" pluginspage = "http://www.macromedia.com/go/getflashplayer" /></object>]]></element></element></element></element>